databridge/__init__.py
databridge/client.py
databridge/exceptions.py
databridge_test-0.1.1.dist-info/METADATA
databridge_test-0.1.1.dist-info/WHEEL
databridge_test-0.1.1.dist-info/RECORD
