Metadata-Version: 2.3
Name: databridge-test
Version: 0.1.1
Summary: DataBridge Python Client
Author-email: Your Name <your.email@example.com>
Requires-Python: >=3.8
Requires-Dist: httpx>=0.24.0
Requires-Dist: pyjwt>=2.0.0
